LICENSE
MANIFEST.in
README.rst
TODO.rst
requirements-dev.txt
requirements.txt
setup.cfg
setup.py
pynsot/__init__.py
pynsot/app.py
pynsot/client.py
pynsot/constants.py
pynsot/dotfile.py
pynsot/models.py
pynsot/serializers.py
pynsot/util.py
pynsot/version.py
pynsot.egg-info/PKG-INFO
pynsot.egg-info/SOURCES.txt
pynsot.egg-info/dependency_links.txt
pynsot.egg-info/entry_points.txt
pynsot.egg-info/requires.txt
pynsot.egg-info/top_level.txt
pynsot/commands/__init__.py
pynsot/commands/callbacks.py
pynsot/commands/cmd_attributes.py
pynsot/commands/cmd_changes.py
pynsot/commands/cmd_circuits.py
pynsot/commands/cmd_devices.py
pynsot/commands/cmd_interfaces.py
pynsot/commands/cmd_networks.py
pynsot/commands/cmd_protocol_types.py
pynsot/commands/cmd_protocols.py
pynsot/commands/cmd_sites.py
pynsot/commands/cmd_values.py
pynsot/commands/types.py
tests/__init__.py
tests/generate_test_data.py
tests/nsot_settings.py
tests/test_app.py
tests/test_client.py
tests/test_dotfile.py
tests/test_models.py
tests/test_util.py
tests/util.py
tests/app/__init__.py
tests/app/test_circuits.py
tests/app/test_protocol_types.py
tests/app/test_protocols.py
tests/fixtures/__init__.py
tests/fixtures/circuits.py
tests/fixtures/protocol_types.py
tests/fixtures/protocols.py