Metadata-Version: 1.2
Name: pynsot
Version: 1.4.1
Summary: Python interface for Network Source of Truth (nsot)
Home-page: https://github.com/dropbox/pynsot
Author: Jathan McCollum
Author-email: jathan@dropbox.com
Maintainer: Jathan McCollum
Maintainer-email: jathan@dropbox.com
License: Apache
Platform: UNKNOWN
Classifier: Programming Language :: Python
Classifier: Topic :: Software Development
Classifier: Topic :: Software Development :: Libraries
Classifier: Topic :: Software Development :: Libraries :: Python Modules
